{"artefact": "golang-project-distribution-packages", "rpm": "golang-github-beorn7-perks-devel-0-0.6.gitb965b61.fc24.noarch.rpm", "product": "Fedora", "build": "golang-github-beorn7-perks-0-0.6.gitb965b61.fc24", "commit": "b965b613227fddccbfffe13eae360ed3fa822f8d", "distribution": "rawhide", "data": [{"main": [], "tests": [], "packages": ["github.com/beorn7/perks/quantile", "github.com/beorn7/perks/topk", "github.com/beorn7/perks/histogram"], "dependencies": [{"dependencies": [{"name": "math", "location": ["stream.go"]}, {"name": "sort", "location": ["stream.go"]}], "qualifier": "quantile", "package": "github.com/beorn7/perks/quantile"}, {"dependencies": [{"name": "sort", "location": ["topk.go"]}], "qualifier": "topk", "package": "github.com/beorn7/perks/topk"}, {"dependencies": [{"name": "container/heap", "location": ["histogram.go"]}, {"name": "math", "location": ["histogram.go"]}, {"name": "sort", "location": ["histogram.go"]}], "qualifier": "histogram", "package": "github.com/beorn7/perks/histogram"}], "ipprefix": "github.com/beorn7/perks"}]}